server.py
datalabs_demo_mcp-0.1.2.dist-info/METADATA
datalabs_demo_mcp-0.1.2.dist-info/WHEEL
datalabs_demo_mcp-0.1.2.dist-info/entry_points.txt
datalabs_demo_mcp-0.1.2.dist-info/top_level.txt
datalabs_demo_mcp-0.1.2.dist-info/RECORD
