Metadata-Version: 2.4
Name: datalabs-demo-mcp
Version: 0.1.2
Requires-Dist: mcp
Requires-Dist: pandas
